{
  "type": "minecraft:crafting_shapeless",
  "ingredients": [
    {
      "item": "minecraft:iron_ore"
    },
    {
      "item": "minecraft:iron_ore"
    },
    {
      "item": "minecraft:iron_ore"
    },
    {
      "item": "minecraft:iron_ore"
    },
    {
      "item": "minecraft:iron_ore"
    },
    {
      "item": "minecraft:iron_ore"
    },
    {
      "item": "rms:mk2_furnace_block"
    },
    {
      "item": "rms:carbon_coal"
    },
    {
      "item": "rms:cupel"
    }
  ],
  "result":
  {
    "item": "rms:mk1_iron_ingot",
    "count": 6
  }
}